dvml/__init__.py
dvml/metrics/__init__.py
dvml/metrics/classification.py
dvml/models/__init__.py
dvml/models/classification_tree.py
dvml/models/linear.py
dvml/models/model.py
dvml/models/random_forest.py
dvml/optimization/__init__.py
dvml/optimization/gradient.py
dvml/utils/__init__.py
dvml/utils/config_utils.py
dvml/utils/data_utils.py
dvml/utils/math_utils.py
dvml-0.5.0.dist-info/LICENSE
dvml-0.5.0.dist-info/METADATA
dvml-0.5.0.dist-info/WHEEL
dvml-0.5.0.dist-info/RECORD
