Metadata-Version: 2.1
Name: dvml
Version: 0.5.0
Summary: 
Author: Daniel Viegas
Author-email: viegasdll@gmail.com
Requires-Python: >=3.9,<4.0
Classifier: Programming Language :: Python :: 3
Classifier: Programming Language :: Python :: 3.9
Classifier: Programming Language :: Python :: 3.10
Classifier: Programming Language :: Python :: 3.11
Requires-Dist: numpy (>=1.24.1,<2.0.0)
